<?xml version="1.0" encoding="UTF-8"?>

 <hw diagnostics="F"
    httpvis="F"
    library="module"
    name="Zynq"
    purpose="4"
    releasestatus="4"
    saverestore="F"
    stoponctrlc="T"
    vendor="xilinx.ovpworld.org"
    verbose="F"
    version="1.0"
    visibility="0">
    <nets name="nets">
        <net name="xadcmux"/>
        <net name="gpio_bank0_in"/>
        <net name="gpio_bank0_out"/>
        <net name="gpio_bank1_in"/>
        <net name="gpio_bank1_out"/>
        <net name="gpio_bank2_in"/>
        <net name="gpio_bank2_out"/>
        <net name="gpio_bank2_oen_out"/>
        <net name="gpio_bank3_in"/>
        <net name="gpio_bank3_out"/>
        <net name="gpio_bank3_oen_out"/>
        <net name="irqf2p0"/>
        <net name="irqf2p1"/>
        <net name="irqf2p2"/>
        <net name="irqf2p3"/>
        <net name="irqf2p4"/>
        <net name="irqf2p5"/>
        <net name="irqf2p6"/>
        <net name="irqf2p7"/>
        <net name="irqf2p8"/>
        <net name="irqf2p9"/>
        <net name="irqf2p10"/>
        <net name="irqf2p11"/>
        <net name="irqf2p12"/>
        <net name="irqf2p13"/>
        <net name="irqf2p14"/>
        <net name="irqf2p15"/>
        <net name="irqf2p16"/>
        <net name="irqf2p17"/>
        <net name="irqf2p18"/>
        <net name="irqf2p19"/>
        <net name="irqp2f0"/>
        <net name="irqp2f1"/>
        <net name="irqp2f2"/>
        <net name="irqp2f3"/>
        <net name="irqp2f4"/>
        <net name="irqp2f5"/>
        <net name="irqp2f6"/>
        <net name="irqp2f7"/>
        <net name="irqp2f8"/>
        <net name="irqp2f9"/>
        <net name="irqp2f10"/>
        <net name="irqp2f11"/>
        <net name="irqp2f12"/>
        <net name="irqp2f13"/>
        <net name="irqp2f14"/>
        <net name="irqp2f15"/>
        <net name="irqp2f16"/>
        <net name="irqp2f17"/>
        <net name="irqp2f18"/>
        <net name="irqp2f19"/>
        <net name="irqp2f20"/>
        <net name="irqp2f21"/>
        <net name="irqp2f22"/>
        <net name="irqp2f23"/>
        <net name="irqp2f24"/>
        <net name="irqp2f25"/>
        <net name="irqp2f26"/>
        <net name="irqp2f27"/>
        <net name="irqp2f28"/>
    </nets>
    <docsection name="doc"
        text="Licensing">
        <doctext name="txt"
            text="Open Source Apache 2.0"/>
    </docsection>
    <docsection name="doc_1"
        text="Description">
        <doctext name="txt"
            text="This module implements the Zynq 7000"/>
    </docsection>
    <docsection name="doc_2"
        text="Limitations">
        <doctext name="txt"
            text="This module provides the instantiation of a Processing Sub-system (Zynq_PS) module and a Programmable Logic (Zynq_PL) module."/>
    </docsection>
    <docsection name="doc_3"
        text="Reference">
        <doctext name="txt"
            text="Zynq-7000 AP SoC Technical Reference Manual UG585 (v1.10) February 23, 2015 (https://www.xilinx.com/support/documentation/user_guides/ug585-Zynq-7000-TRM.pdf)"/>
    </docsection>
    <module name="Zynq_PS">
        <vlnvreference library="module"
            name="Zynq_PS"
            vendor="xilinx.ovpworld.org"
            version="1.0"/>
        <attribute content="psclock"
            name="psclock"/>
        <attribute content="armmips"
            name="armmips"/>
        <attribute content="board"
            name="board"/>
        <attribute content="flashtype"
            name="flashtype"/>
        <busportconnection connection="i2cBus"
            name="extPortI2C"/>
        <netportconnection connection="xadcmux"
            name="extPortXADCMux"/>
        <busportconnection connection="icBus"
            name="extPort"/>
        <netportconnection connection="gpio_bank0_out"
            name="gpio_bank0_outP"/>
        <netportconnection connection="gpio_bank0_in"
            name="gpio_bank0_inP"/>
        <netportconnection connection="gpio_bank1_out"
            name="gpio_bank1_outP"/>
        <netportconnection connection="gpio_bank1_in"
            name="gpio_bank1_inP"/>
        <netportconnection connection="gpio_bank2_out"
            name="gpio_bank2_outP"/>
        <netportconnection connection="gpio_bank2_oen_out"
            name="gpio_bank2_oen_outP"/>
        <netportconnection connection="gpio_bank2_in"
            name="gpio_bank2_inP"/>
        <netportconnection connection="gpio_bank3_out"
            name="gpio_bank3_outP"/>
        <netportconnection connection="gpio_bank3_oen_out"
            name="gpio_bank3_oen_outP"/>
        <netportconnection connection="gpio_bank3_in"
            name="gpio_bank3_inP"/>
        <netportconnection connection="irqf2p0"
            name="irqf2p0_inP"/>
        <netportconnection connection="irqf2p1"
            name="irqf2p1_inP"/>
        <netportconnection connection="irqf2p2"
            name="irqf2p2_inP"/>
        <netportconnection connection="irqf2p3"
            name="irqf2p3_inP"/>
        <netportconnection connection="irqf2p4"
            name="irqf2p4_inP"/>
        <netportconnection connection="irqf2p5"
            name="irqf2p5_inP"/>
        <netportconnection connection="irqf2p6"
            name="irqf2p6_inP"/>
        <netportconnection connection="irqf2p7"
            name="irqf2p7_inP"/>
        <netportconnection connection="irqf2p8"
            name="irqf2p8_inP"/>
        <netportconnection connection="irqf2p9"
            name="irqf2p9_inP"/>
        <netportconnection connection="irqf2p10"
            name="irqf2p10_inP"/>
        <netportconnection connection="irqf2p11"
            name="irqf2p11_inP"/>
        <netportconnection connection="irqf2p12"
            name="irqf2p12_inP"/>
        <netportconnection connection="irqf2p13"
            name="irqf2p13_inP"/>
        <netportconnection connection="irqf2p14"
            name="irqf2p14_inP"/>
        <netportconnection connection="irqf2p15"
            name="irqf2p15_inP"/>
        <netportconnection connection="irqf2p16"
            name="irqf2p16_inP"/>
        <netportconnection connection="irqf2p17"
            name="irqf2p17_inP"/>
        <netportconnection connection="irqf2p18"
            name="irqf2p18_inP"/>
        <netportconnection connection="irqf2p19"
            name="irqf2p19_inP"/>
        <netportconnection connection="irqp2f0"
            name="irqp2f0_outP"/>
        <netportconnection connection="irqp2f1"
            name="irqp2f1_outP"/>
        <netportconnection connection="irqp2f2"
            name="irqp2f2_outP"/>
        <netportconnection connection="irqp2f3"
            name="irqp2f3_outP"/>
        <netportconnection connection="irqp2f4"
            name="irqp2f4_outP"/>
        <netportconnection connection="irqp2f5"
            name="irqp2f5_outP"/>
        <netportconnection connection="irqp2f6"
            name="irqp2f6_outP"/>
        <netportconnection connection="irqp2f7"
            name="irqp2f7_outP"/>
        <netportconnection connection="irqp2f8"
            name="irqp2f8_outP"/>
        <netportconnection connection="irqp2f9"
            name="irqp2f9_outP"/>
        <netportconnection connection="irqp2f10"
            name="irqp2f10_outP"/>
        <netportconnection connection="irqp2f11"
            name="irqp2f11_outP"/>
        <netportconnection connection="irqp2f12"
            name="irqp2f12_outP"/>
        <netportconnection connection="irqp2f13"
            name="irqp2f13_outP"/>
        <netportconnection connection="irqp2f14"
            name="irqp2f14_outP"/>
        <netportconnection connection="irqp2f15"
            name="irqp2f15_outP"/>
        <netportconnection connection="irqp2f16"
            name="irqp2f16_outP"/>
        <netportconnection connection="irqp2f17"
            name="irqp2f17_outP"/>
        <netportconnection connection="irqp2f18"
            name="irqp2f18_outP"/>
        <netportconnection connection="irqp2f19"
            name="irqp2f19_outP"/>
        <netportconnection connection="irqp2f20"
            name="irqp2f20_outP"/>
        <netportconnection connection="irqp2f21"
            name="irqp2f21_outP"/>
        <netportconnection connection="irqp2f22"
            name="irqp2f22_outP"/>
        <netportconnection connection="irqp2f23"
            name="irqp2f23_outP"/>
        <netportconnection connection="irqp2f24"
            name="irqp2f24_outP"/>
        <netportconnection connection="irqp2f25"
            name="irqp2f25_outP"/>
        <netportconnection connection="irqp2f26"
            name="irqp2f26_outP"/>
        <netportconnection connection="irqp2f27"
            name="irqp2f27_outP"/>
        <netportconnection connection="irqp2f28"
            name="irqp2f28_outP"/>
    </module>
    <formalattribute defaultvalue="33"
        name="psclock"
        type="Uns32"/>
    <formalattribute defaultvalue="500"
        name="armmips"
        type="Uns32"/>
    <formalattribute name="board"
        type="String"/>
    <formalattribute name="flashtype"
        type="String"/>
    <busportconnection connection="i2cBus"
        mustbeconnected="F"
        name="extPortI2C"/>
    <bus addresswidth="16"
        name="i2cBus"/>
    <netportconnection connection="xadcmux"
        mustbeconnected="F"
        name="extPortXADCMux"/>
    <formalattribute defaultvalue="Zynq_PL_Default"
        name="plmoduletype"
        type="string"/>
    <formalattribute defaultvalue="xilinx.ovpworld.org"
        name="plmodulevendor"
        type="string"/>
    <module name="Zynq_PL">
        <vlnvreference library="module"
            name="plmoduletype"
            vendor="plmodulevendor"
            version="1.0"/>
        <busportconnection connection="icBus"
            name="extPort"/>
        <netportconnection connection="gpio_bank2_out"
            name="gpio_bank2_outP"/>
        <netportconnection connection="gpio_bank2_oen_out"
            name="gpio_bank2_oen_outP"/>
        <netportconnection connection="gpio_bank2_in"
            name="gpio_bank2_inP"/>
        <netportconnection connection="gpio_bank3_out"
            name="gpio_bank3_outP"/>
        <netportconnection connection="gpio_bank3_oen_out"
            name="gpio_bank3_oen_outP"/>
        <netportconnection connection="gpio_bank3_in"
            name="gpio_bank3_inP"/>
        <netportconnection connection="irqf2p0"
            name="irqf2p0_outP"/>
        <netportconnection connection="irqf2p1"
            name="irqf2p1_outP"/>
        <netportconnection connection="irqf2p2"
            name="irqf2p2_outP"/>
        <netportconnection connection="irqf2p3"
            name="irqf2p3_outP"/>
        <netportconnection connection="irqf2p4"
            name="irqf2p4_outP"/>
        <netportconnection connection="irqf2p5"
            name="irqf2p5_outP"/>
        <netportconnection connection="irqf2p6"
            name="irqf2p6_outP"/>
        <netportconnection connection="irqf2p7"
            name="irqf2p7_outP"/>
        <netportconnection connection="irqf2p8"
            name="irqf2p8_outP"/>
        <netportconnection connection="irqf2p9"
            name="irqf2p9_outP"/>
        <netportconnection connection="irqf2p10"
            name="irqf2p10_outP"/>
        <netportconnection connection="irqf2p11"
            name="irqf2p11_outP"/>
        <netportconnection connection="irqf2p12"
            name="irqf2p12_outP"/>
        <netportconnection connection="irqf2p13"
            name="irqf2p13_outP"/>
        <netportconnection connection="irqf2p14"
            name="irqf2p14_outP"/>
        <netportconnection connection="irqf2p15"
            name="irqf2p15_outP"/>
        <netportconnection connection="irqf2p16"
            name="irqf2p16_outP"/>
        <netportconnection connection="irqf2p17"
            name="irqf2p17_outP"/>
        <netportconnection connection="irqf2p18"
            name="irqf2p18_outP"/>
        <netportconnection connection="irqf2p19"
            name="irqf2p19_outP"/>
        <netportconnection connection="irqp2f0"
            name="irqp2f0_inP"/>
        <netportconnection connection="irqp2f1"
            name="irqp2f1_inP"/>
        <netportconnection connection="irqp2f2"
            name="irqp2f2_inP"/>
        <netportconnection connection="irqp2f3"
            name="irqp2f3_inP"/>
        <netportconnection connection="irqp2f4"
            name="irqp2f4_inP"/>
        <netportconnection connection="irqp2f5"
            name="irqp2f5_inP"/>
        <netportconnection connection="irqp2f6"
            name="irqp2f6_inP"/>
        <netportconnection connection="irqp2f7"
            name="irqp2f7_inP"/>
        <netportconnection connection="irqp2f8"
            name="irqp2f8_inP"/>
        <netportconnection connection="irqp2f9"
            name="irqp2f9_inP"/>
        <netportconnection connection="irqp2f10"
            name="irqp2f10_inP"/>
        <netportconnection connection="irqp2f11"
            name="irqp2f11_inP"/>
        <netportconnection connection="irqp2f12"
            name="irqp2f12_inP"/>
        <netportconnection connection="irqp2f13"
            name="irqp2f13_inP"/>
        <netportconnection connection="irqp2f14"
            name="irqp2f14_inP"/>
        <netportconnection connection="irqp2f15"
            name="irqp2f15_inP"/>
        <netportconnection connection="irqp2f16"
            name="irqp2f16_inP"/>
        <netportconnection connection="irqp2f17"
            name="irqp2f17_inP"/>
        <netportconnection connection="irqp2f18"
            name="irqp2f18_inP"/>
        <netportconnection connection="irqp2f19"
            name="irqp2f19_inP"/>
        <netportconnection connection="irqp2f20"
            name="irqp2f20_inP"/>
        <netportconnection connection="irqp2f21"
            name="irqp2f21_inP"/>
        <netportconnection connection="irqp2f22"
            name="irqp2f22_inP"/>
        <netportconnection connection="irqp2f23"
            name="irqp2f23_inP"/>
        <netportconnection connection="irqp2f24"
            name="irqp2f24_inP"/>
        <netportconnection connection="irqp2f25"
            name="irqp2f25_inP"/>
        <netportconnection connection="irqp2f26"
            name="irqp2f26_inP"/>
        <netportconnection connection="irqp2f27"
            name="irqp2f27_inP"/>
        <netportconnection connection="irqp2f28"
            name="irqp2f28_inP"/>
    </module>
    <bus addresswidth="32"
        name="icBus"/>
    <netportconnection connection="gpio_bank0_out"
        mustbeconnected="F"
        name="gpio_bank0_outP"/>
    <netportconnection connection="gpio_bank1_out"
        mustbeconnected="F"
        name="gpio_bank1_outP"/>
    <netportconnection connection="gpio_bank0_in"
        mustbeconnected="F"
        name="gpio_bank0_inP"/>
    <netportconnection connection="gpio_bank1_in"
        mustbeconnected="F"
        name="gpio_bank1_inP"/>
    <attribute content="1"
        name="stoponcontrolc"/>
    <fileversion major="1"
        minor="0"
        name="_version_0"/>
 </hw>
